api_server/__init__.py
api_server/routes/__init__.py
api_server/routes/internal/__init__.py
api_server/routes/internal/internal_routes.py
api_server/services/__init__.py
api_server/services/file_service.py
api_server/services/terminal_service.py
api_server/utils/__init__.py
api_server/utils/file_operations.py
app/__init__.py
app/app_settings.py
app/frontend_management.py
app/logger.py
app/user_manager.py
comfy/__init__.py
comfy/checkpoint_pickle.py
comfy/cli_args.py
comfy/clip_model.py
comfy/clip_vision.py
comfy/comfy_types.py
comfy/conds.py
comfy/controlnet.py
comfy/diffusers_convert.py
comfy/diffusers_load.py
comfy/float.py
comfy/gligen.py
comfy/latent_formats.py
comfy/lora.py
comfy/lora_convert.py
comfy/model_base.py
comfy/model_detection.py
comfy/model_management.py
comfy/model_patcher.py
comfy/model_sampling.py
comfy/ops.py
comfy/options.py
comfy/sample.py
comfy/sampler_helpers.py
comfy/samplers.py
comfy/sd.py
comfy/sd1_clip.py
comfy/sdxl_clip.py
comfy/supported_models.py
comfy/supported_models_base.py
comfy/utils.py
comfy/cldm/__init__.py
comfy/cldm/cldm.py
comfy/cldm/control_types.py
comfy/cldm/mmdit.py
comfy/extra_samplers/__init__.py
comfy/extra_samplers/uni_pc.py
comfy/k_diffusion/__init__.py
comfy/k_diffusion/deis.py
comfy/k_diffusion/sampling.py
comfy/k_diffusion/utils.py
comfy/ldm/__init__.py
comfy/ldm/common_dit.py
comfy/ldm/util.py
comfy/ldm/audio/__init__.py
comfy/ldm/audio/autoencoder.py
comfy/ldm/audio/dit.py
comfy/ldm/audio/embedders.py
comfy/ldm/aura/__init__.py
comfy/ldm/aura/mmdit.py
comfy/ldm/cascade/__init__.py
comfy/ldm/cascade/common.py
comfy/ldm/cascade/controlnet.py
comfy/ldm/cascade/stage_a.py
comfy/ldm/cascade/stage_b.py
comfy/ldm/cascade/stage_c.py
comfy/ldm/cascade/stage_c_coder.py
comfy/ldm/flux/__init__.py
comfy/ldm/flux/controlnet.py
comfy/ldm/flux/layers.py
comfy/ldm/flux/math.py
comfy/ldm/flux/model.py
comfy/ldm/flux/redux.py
comfy/ldm/genmo/__init__.py
comfy/ldm/genmo/joint_model/__init__.py
notcomfy-0.1.0.dist-info/LICENSE
notcomfy-0.1.0.dist-info/METADATA
notcomfy-0.1.0.dist-info/WHEEL
notcomfy-0.1.0.dist-info/top_level.txt
notcomfy-0.1.0.dist-info/RECORD
