Metadata-Version: 2.1
Name: notcomfy
Version: 0.1.0
License-File: LICENSE
Requires-Dist: torch
Requires-Dist: torchsde
Requires-Dist: torchvision
Requires-Dist: torchaudio
Requires-Dist: einops
Requires-Dist: transformers>=4.28.1
Requires-Dist: tokenizers>=0.13.3
Requires-Dist: sentencepiece
Requires-Dist: safetensors>=0.4.2
Requires-Dist: aiohttp
Requires-Dist: pyyaml
Requires-Dist: Pillow
Requires-Dist: scipy
Requires-Dist: tqdm
Requires-Dist: psutil
Requires-Dist: kornia>=0.7.1
Requires-Dist: spandrel
Requires-Dist: soundfile
